icebergdiag/__init__.py
icebergdiag/cli.py
icebergdiag/diagnostics/__init__.py
icebergdiag/diagnostics/manager.py
icebergdiag/diagnostics/requester.py
icebergdiag/diagnostics/response.py
icebergdiag/exceptions.py
icebergdiag/metrics/__init__.py
icebergdiag/metrics/table.py
icebergdiag/metrics/table_metric.py
icebergdiag/metrics/table_metrics.py
icebergdiag/metrics/table_metrics_displayer.py
icebergdiag/utils.py
iceberg_diag-0.1.5.dist-info/LICENSE
iceberg_diag-0.1.5.dist-info/METADATA
iceberg_diag-0.1.5.dist-info/WHEEL
iceberg_diag-0.1.5.dist-info/entry_points.txt
iceberg_diag-0.1.5.dist-info/RECORD
