Metadata-Version: 2.1
Name: iceberg-diag
Version: 0.1.5
Summary: Upsolver Iceberg Auditor CLI
Home-page: https://github.com/Upsolver/iceberg-diag
License: MIT
Author: Upsolver
Author-email: developers@upsolver.com
Requires-Python: >=3.8,<4.0
Classifier: License :: OSI Approved :: MIT License
Classifier: Programming Language :: Python :: 3
Classifier: Programming Language :: Python :: 3.8
Classifier: Programming Language :: Python :: 3.9
Classifier: Programming Language :: Python :: 3.10
Classifier: Programming Language :: Python :: 3.11
Classifier: Programming Language :: Python :: 3.12
Requires-Dist: boto3 (>=1.34.0,<2.0.0)
Requires-Dist: botocore (>=1.34.0,<2.0.0)
Requires-Dist: pyiceberg[glue,s3fs] (>=0.5.1,<0.6.0)
Requires-Dist: requests (>=2.31.0,<3.0.0)
Requires-Dist: rich (>=13.7.0,<14.0.0)
